<annotation>
	<folder>JPEGImages</folder>
	<filename>00413.jpg</filename>
	<path>D:\database\VOCdevkit\VOC2007\JPEGImages\00413.jpg</path>
	<source>
		<database>Unknown</database>
	</source>
	<size>
		<width>256</width>
		<height>256</height>
		<depth>3</depth>
	</size>
	<segmented>0</segmented>
	<object>
		<name>incorrectlyWear</name>
		<pose>Unspecified</pose>
		<truncated>0</truncated>
		<difficult>0</difficult>
		<bndbox>
			<xmin>62</xmin>
			<ymin>47</ymin>
			<xmax>101</xmax>
			<ymax>95</ymax>
		</bndbox>
	</object>
	<object>
		<name>noWear</name>
		<pose>Unspecified</pose>
		<truncated>0</truncated>
		<difficult>0</difficult>
		<bndbox>
			<xmin>129</xmin>
			<ymin>137</ymin>
			<xmax>168</xmax>
			<ymax>181</ymax>
		</bndbox>
	</object>
</annotation>