<annotation>
	<folder>JPEGImages</folder>
	<filename>00748.jpg</filename>
	<path>D:\database\VOCdevkit\VOC2007\JPEGImages\00748.jpg</path>
	<source>
		<database>Unknown</database>
	</source>
	<size>
		<width>256</width>
		<height>256</height>
		<depth>3</depth>
	</size>
	<segmented>0</segmented>
	<object>
		<name>noWear</name>
		<pose>Unspecified</pose>
		<truncated>0</truncated>
		<difficult>0</difficult>
		<bndbox>
			<xmin>56</xmin>
			<ymin>72</ymin>
			<xmax>92</xmax>
			<ymax>111</ymax>
		</bndbox>
	</object>
	<object>
		<name>correctlyWear</name>
		<pose>Unspecified</pose>
		<truncated>0</truncated>
		<difficult>0</difficult>
		<bndbox>
			<xmin>154</xmin>
			<ymin>51</ymin>
			<xmax>195</xmax>
			<ymax>99</ymax>
		</bndbox>
	</object>
	<object>
		<name>noWear</name>
		<pose>Unspecified</pose>
		<truncated>0</truncated>
		<difficult>0</difficult>
		<bndbox>
			<xmin>216</xmin>
			<ymin>92</ymin>
			<xmax>227</xmax>
			<ymax>110</ymax>
		</bndbox>
	</object>
</annotation>