<annotation>
	<folder>data</folder>
	<filename>part3_20200213_ljx_00033.jpg</filename>
	<path>E:\Software\windows_v1.8.1\data\data\part3_20200213_ljx_00033.jpg</path>
	<source>
		<database>Unknown</database>
	</source>
	<size>
		<width>2340</width>
		<height>1080</height>
		<depth>3</depth>
	</size>
	<segmented>0</segmented>
	<object>
		<name>correctlyWear</name>
		<pose>Unspecified</pose>
		<truncated>0</truncated>
		<difficult>0</difficult>
		<bndbox>
			<xmin>1495</xmin>
			<ymin>135</ymin>
			<xmax>1719</xmax>
			<ymax>378</ymax>
		</bndbox>
	</object>
	<object>
		<name>correctlyWear</name>
		<pose>Unspecified</pose>
		<truncated>0</truncated>
		<difficult>0</difficult>
		<bndbox>
			<xmin>1348</xmin>
			<ymin>315</ymin>
			<xmax>1549</xmax>
			<ymax>486</ymax>
		</bndbox>
	</object>
	<object>
		<name>correctlyWear</name>
		<pose>Unspecified</pose>
		<truncated>0</truncated>
		<difficult>0</difficult>
		<bndbox>
			<xmin>1124</xmin>
			<ymin>285</ymin>
			<xmax>1284</xmax>
			<ymax>434</ymax>
		</bndbox>
	</object>
	<object>
		<name>correctlyWear</name>
		<pose>Unspecified</pose>
		<truncated>0</truncated>
		<difficult>0</difficult>
		<bndbox>
			<xmin>812</xmin>
			<ymin>438</ymin>
			<xmax>926</xmax>
			<ymax>542</ymax>
		</bndbox>
	</object>
	<object>
		<name>correctlyWear</name>
		<pose>Unspecified</pose>
		<truncated>0</truncated>
		<difficult>0</difficult>
		<bndbox>
			<xmin>600</xmin>
			<ymin>335</ymin>
			<xmax>788</xmax>
			<ymax>512</ymax>
		</bndbox>
	</object>
</annotation>