<annotation>
	<folder>JPEGImages</folder>
	<filename>03497.jpg</filename>
	<path>D:\database\VOCdevkit\VOC2007\JPEGImages\03497.jpg</path>
	<source>
		<database>Unknown</database>
	</source>
	<size>
		<width>2340</width>
		<height>1080</height>
		<depth>3</depth>
	</size>
	<segmented>0</segmented>
	<object>
		<name>correctlyWear</name>
		<pose>Unspecified</pose>
		<truncated>0</truncated>
		<difficult>0</difficult>
		<bndbox>
			<xmin>1224</xmin>
			<ymin>333</ymin>
			<xmax>1344</xmax>
			<ymax>465</ymax>
		</bndbox>
	</object>
	<object>
		<name>correctlyWear</name>
		<pose>Unspecified</pose>
		<truncated>0</truncated>
		<difficult>0</difficult>
		<bndbox>
			<xmin>967</xmin>
			<ymin>377</ymin>
			<xmax>1060</xmax>
			<ymax>458</ymax>
		</bndbox>
	</object>
	<object>
		<name>correctlyWear</name>
		<pose>Unspecified</pose>
		<truncated>0</truncated>
		<difficult>0</difficult>
		<bndbox>
			<xmin>749</xmin>
			<ymin>308</ymin>
			<xmax>836</xmax>
			<ymax>384</ymax>
		</bndbox>
	</object>
	<object>
		<name>correctlyWear</name>
		<pose>Unspecified</pose>
		<truncated>0</truncated>
		<difficult>0</difficult>
		<bndbox>
			<xmin>656</xmin>
			<ymin>175</ymin>
			<xmax>702</xmax>
			<ymax>231</ymax>
		</bndbox>
	</object>
	<object>
		<name>correctlyWear</name>
		<pose>Unspecified</pose>
		<truncated>0</truncated>
		<difficult>0</difficult>
		<bndbox>
			<xmin>899</xmin>
			<ymin>310</ymin>
			<xmax>972</xmax>
			<ymax>384</ymax>
		</bndbox>
	</object>
</annotation>