<annotation>
	<folder>JPEGImages</folder>
	<filename>03636.jpg</filename>
	<path>D:\database\VOCdevkit\VOC2007\JPEGImages\03636.jpg</path>
	<source>
		<database>Unknown</database>
	</source>
	<size>
		<width>640</width>
		<height>794</height>
		<depth>3</depth>
	</size>
	<segmented>0</segmented>
	<object>
		<name>noWear</name>
		<pose>Unspecified</pose>
		<truncated>0</truncated>
		<difficult>0</difficult>
		<bndbox>
			<xmin>235</xmin>
			<ymin>549</ymin>
			<xmax>372</xmax>
			<ymax>685</ymax>
		</bndbox>
	</object>
	<object>
		<name>noWear</name>
		<pose>Unspecified</pose>
		<truncated>0</truncated>
		<difficult>0</difficult>
		<bndbox>
			<xmin>416</xmin>
			<ymin>458</ymin>
			<xmax>571</xmax>
			<ymax>583</ymax>
		</bndbox>
	</object>
	<object>
		<name>noWear</name>
		<pose>Unspecified</pose>
		<truncated>0</truncated>
		<difficult>0</difficult>
		<bndbox>
			<xmin>48</xmin>
			<ymin>163</ymin>
			<xmax>120</xmax>
			<ymax>260</ymax>
		</bndbox>
	</object>
	<object>
		<name>noWear</name>
		<pose>Unspecified</pose>
		<truncated>0</truncated>
		<difficult>0</difficult>
		<bndbox>
			<xmin>500</xmin>
			<ymin>160</ymin>
			<xmax>555</xmax>
			<ymax>218</ymax>
		</bndbox>
	</object>
	<object>
		<name>noWear</name>
		<pose>Unspecified</pose>
		<truncated>0</truncated>
		<difficult>0</difficult>
		<bndbox>
			<xmin>208</xmin>
			<ymin>85</ymin>
			<xmax>258</xmax>
			<ymax>189</ymax>
		</bndbox>
	</object>
</annotation>