<annotation>
	<folder>data</folder>
	<filename>part3_20200213_ljx_00081.jpg</filename>
	<path>E:\Software\windows_v1.8.1\data\data\part3_20200213_ljx_00081.jpg</path>
	<source>
		<database>Unknown</database>
	</source>
	<size>
		<width>2340</width>
		<height>1080</height>
		<depth>3</depth>
	</size>
	<segmented>0</segmented>
	<object>
		<name>correctlyWear</name>
		<pose>Unspecified</pose>
		<truncated>0</truncated>
		<difficult>0</difficult>
		<bndbox>
			<xmin>1894</xmin>
			<ymin>199</ymin>
			<xmax>2127</xmax>
			<ymax>434</ymax>
		</bndbox>
	</object>
	<object>
		<name>correctlyWear</name>
		<pose>Unspecified</pose>
		<truncated>0</truncated>
		<difficult>0</difficult>
		<bndbox>
			<xmin>1509</xmin>
			<ymin>239</ymin>
			<xmax>1692</xmax>
			<ymax>421</ymax>
		</bndbox>
	</object>
	<object>
		<name>correctlyWear</name>
		<pose>Unspecified</pose>
		<truncated>0</truncated>
		<difficult>0</difficult>
		<bndbox>
			<xmin>1422</xmin>
			<ymin>289</ymin>
			<xmax>1507</xmax>
			<ymax>384</ymax>
		</bndbox>
	</object>
	<object>
		<name>correctlyWear</name>
		<pose>Unspecified</pose>
		<truncated>0</truncated>
		<difficult>0</difficult>
		<bndbox>
			<xmin>1299</xmin>
			<ymin>363</ymin>
			<xmax>1375</xmax>
			<ymax>444</ymax>
		</bndbox>
	</object>
	<object>
		<name>correctlyWear</name>
		<pose>Unspecified</pose>
		<truncated>0</truncated>
		<difficult>0</difficult>
		<bndbox>
			<xmin>585</xmin>
			<ymin>253</ymin>
			<xmax>705</xmax>
			<ymax>358</ymax>
		</bndbox>
	</object>
</annotation>