<annotation>
	<folder>JPEGImages</folder>
	<filename>03853.jpg</filename>
	<path>D:\database\VOCdevkit\VOC2007\JPEGImages\03853.jpg</path>
	<source>
		<database>Unknown</database>
	</source>
	<size>
		<width>2340</width>
		<height>1080</height>
		<depth>3</depth>
	</size>
	<segmented>0</segmented>
	<object>
		<name>correctlyWear</name>
		<pose>Unspecified</pose>
		<truncated>0</truncated>
		<difficult>0</difficult>
		<bndbox>
			<xmin>320</xmin>
			<ymin>400</ymin>
			<xmax>423</xmax>
			<ymax>471</ymax>
		</bndbox>
	</object>
	<object>
		<name>correctlyWear</name>
		<pose>Unspecified</pose>
		<truncated>0</truncated>
		<difficult>0</difficult>
		<bndbox>
			<xmin>581</xmin>
			<ymin>409</ymin>
			<xmax>627</xmax>
			<ymax>463</ymax>
		</bndbox>
	</object>
	<object>
		<name>correctlyWear</name>
		<pose>Unspecified</pose>
		<truncated>0</truncated>
		<difficult>0</difficult>
		<bndbox>
			<xmin>744</xmin>
			<ymin>437</ymin>
			<xmax>817</xmax>
			<ymax>505</ymax>
		</bndbox>
	</object>
	<object>
		<name>correctlyWear</name>
		<pose>Unspecified</pose>
		<truncated>0</truncated>
		<difficult>0</difficult>
		<bndbox>
			<xmin>1144</xmin>
			<ymin>415</ymin>
			<xmax>1220</xmax>
			<ymax>489</ymax>
		</bndbox>
	</object>
	<object>
		<name>correctlyWear</name>
		<pose>Unspecified</pose>
		<truncated>0</truncated>
		<difficult>0</difficult>
		<bndbox>
			<xmin>1322</xmin>
			<ymin>416</ymin>
			<xmax>1352</xmax>
			<ymax>455</ymax>
		</bndbox>
	</object>
	<object>
		<name>correctlyWear</name>
		<pose>Unspecified</pose>
		<truncated>0</truncated>
		<difficult>0</difficult>
		<bndbox>
			<xmin>1404</xmin>
			<ymin>419</ymin>
			<xmax>1440</xmax>
			<ymax>456</ymax>
		</bndbox>
	</object>
	<object>
		<name>correctlyWear</name>
		<pose>Unspecified</pose>
		<truncated>0</truncated>
		<difficult>0</difficult>
		<bndbox>
			<xmin>1791</xmin>
			<ymin>416</ymin>
			<xmax>1824</xmax>
			<ymax>452</ymax>
		</bndbox>
	</object>
	<object>
		<name>correctlyWear</name>
		<pose>Unspecified</pose>
		<truncated>0</truncated>
		<difficult>0</difficult>
		<bndbox>
			<xmin>1031</xmin>
			<ymin>401</ymin>
			<xmax>1057</xmax>
			<ymax>436</ymax>
		</bndbox>
	</object>
	<object>
		<name>correctlyWear</name>
		<pose>Unspecified</pose>
		<truncated>0</truncated>
		<difficult>0</difficult>
		<bndbox>
			<xmin>1386</xmin>
			<ymin>378</ymin>
			<xmax>1415</xmax>
			<ymax>412</ymax>
		</bndbox>
	</object>
</annotation>